{"cameraMode":{"drawMode":0,"name":"Shaded","section":"Shading Mode"},"sceneLighting":true,"audioPlay":false,"sceneViewState":{"showFog":true,"showMaterialUpdate":false,"showSkybox":true,"showFlares":true,"showImageEffects":true,"showParticleSystems":true,"showVisualEffectGraphs":true,"m_FxEnabled":true},"in2DMode":false,"pivot":{"x":111.1708755493164,"y":138.33338928222657,"z":-493.8940734863281},"rotation":{"x":0.008142958395183087,"y":-0.9915880560874939,"z":-0.0937773585319519,"w":-0.09720098227262497},"size":242.4871063232422,"orthographic":false}